picoplugin/__init__.py
picoplugin/__main__.py
picoplugin/cmds.py
picoplugin/config.py
picoplugin/templates/cargo.toml.j2
picoplugin/templates/lib.rs.j2
picoplugin/templates/manifest.yaml.j2
picoplugin/templates/service.rs.j2
picoplugin-0.0.1.dist-info/LICENSE
picoplugin-0.0.1.dist-info/METADATA
picoplugin-0.0.1.dist-info/WHEEL
picoplugin-0.0.1.dist-info/entry_points.txt
picoplugin-0.0.1.dist-info/top_level.txt
picoplugin-0.0.1.dist-info/RECORD
